{
  "dex": 58,
  "speciesName": "Growlithe",
  "speciesId": "growlithe",
  "baseStats": {
    "atk": 136,
    "def": 93,
    "hp": 146
  },
  "defaultIvs": {
    "1500": {
      "level": 50,
      "ivs": {
        "atk": 15,
        "def": 15,
        "hp": 15
      }
    },
    "2500": {
      "level": 50,
      "ivs": {
        "atk": 15,
        "def": 15,
        "hp": 15
      }
    }
  },
  "types": [
    "fire"
  ],
  "fastMoves": [
    "BITE",
    "EMBER"
  ],
  "chargedMoves": [
    "BODY_SLAM",
    "FLAME_WHEEL",
    "FLAMETHROWER"
  ],
  "released": true,
  "tags": [
    "shadoweligible"
  ]
}