{
  "dex": 470,
  "speciesName": "Leafeon",
  "speciesId": "leafeon",
  "baseStats": {
    "atk": 216,
    "def": 219,
    "hp": 163
  },
  "defaultIvs": {
    "1500": {
      "level": 18.5,
      "ivs": {
        "atk": 7,
        "def": 13,
        "hp": 15
      }
    },
    "2500": {
      "level": 32,
      "ivs": {
        "atk": 5,
        "def": 14,
        "hp": 15
      }
    }
  },
  "types": [
    "grass"
  ],
  "fastMoves": [
    "QUICK_ATTACK",
    "RAZOR_LEAF",
    "BULLET_SEED"
  ],
  "chargedMoves": [
    "ENERGY_BALL",
    "LEAF_BLADE",
    "SOLAR_BEAM",
    "LAST_RESORT"
  ],
  "released": true
}