{
  "dex": 511,
  "speciesName": "Pansage",
  "speciesId": "pansage",
  "baseStats": {
    "atk": 104,
    "def": 94,
    "hp": 137
  },
  "defaultIvs": {
    "1500": {
      "level": 50,
      "ivs": {
        "atk": 15,
        "def": 15,
        "hp": 15
      }
    },
    "2500": {
      "level": 50,
      "ivs": {
        "atk": 15,
        "def": 15,
        "hp": 15
      }
    }
  },
  "types": [
    "grass"
  ],
  "fastMoves": [
    "SCRATCH",
    "VINE_WHIP"
  ],
  "chargedMoves": [
    "ENERGY_BALL",
    "SEED_BOMB",
    "CRUNCH"
  ],
  "released": true,
  "tags": [
    "regional"
  ]
}