{
  "dex": 755,
  "speciesName": "Morelull",
  "speciesId": "morelull",
  "baseStats": {
    "atk": 108,
    "def": 119,
    "hp": 120
  },
  "defaultIvs": {
    "1500": {
      "level": 50,
      "ivs": {
        "atk": 15,
        "def": 15,
        "hp": 15
      }
    },
    "2500": {
      "level": 50,
      "ivs": {
        "atk": 15,
        "def": 15,
        "hp": 15
      }
    }
  },
  "types": [
    "grass",
    "fairy"
  ],
  "fastMoves": [
    "ASTONISH"
  ],
  "chargedMoves": [
    "DAZZLING_GLEAM",
    "SEED_BOMB"
  ],
  "released": true
}