{
  "dex": 898,
  "speciesName": "Calyrex",
  "speciesId": "calyrex",
  "baseStats": {
    "atk": 162,
    "def": 162,
    "hp": 225
  },
  "defaultIvs": {
    "1500": {
      "level": 25,
      "ivs": {
        "atk": 4,
        "def": 15,
        "hp": 7
      }
    },
    "2500": {
      "level": 49,
      "ivs": {
        "atk": 13,
        "def": 15,
        "hp": 12
      }
    }
  },
  "types": [
    "psychic",
    "grass"
  ],
  "fastMoves": [
    "POUND",
    "CONFUSION"
  ],
  "chargedMoves": [
    "PSYSHOCK",
    "PSYCHIC",
    "ENERGY_BALL"
  ],
  "released": false
}