{
  "dex": 17,
  "speciesName": "Pidgeotto",
  "speciesId": "pidgeotto",
  "baseStats": {
    "atk": 117,
    "def": 105,
    "hp": 160
  },
  "defaultIvs": {
    "1500": {
      "level": 50,
      "ivs": {
        "atk": 15,
        "def": 15,
        "hp": 15
      }
    },
    "2500": {
      "level": 50,
      "ivs": {
        "atk": 15,
        "def": 15,
        "hp": 15
      }
    }
  },
  "types": [
    "normal",
    "flying"
  ],
  "fastMoves": [
    "STEEL_WING",
    "WING_ATTACK"
  ],
  "chargedMoves": [
    "AERIAL_ACE",
    "AIR_CUTTER",
    "TWISTER"
  ],
  "released": true,
  "tags": [
    "shadoweligible"
  ]
}