{
  "dex": 51,
  "speciesName": "Dugtrio",
  "speciesId": "dugtrio",
  "baseStats": {
    "atk": 167,
    "def": 136,
    "hp": 111
  },
  "defaultIvs": {
    "1500": {
      "level": 41.5,
      "ivs": {
        "atk": 4,
        "def": 15,
        "hp": 14
      }
    },
    "2500": {
      "level": 50,
      "ivs": {
        "atk": 15,
        "def": 15,
        "hp": 15
      }
    }
  },
  "types": [
    "ground"
  ],
  "fastMoves": [
    "MUD_SHOT",
    "MUD_SLAP",
    "SUCKER_PUNCH"
  ],
  "chargedMoves": [
    "EARTHQUAKE",
    "MUD_BOMB",
    "STONE_EDGE"
  ],
  "released": true,
  "tags": [
    "shadoweligible"
  ]
}