{
  "dex": 836,
  "speciesName": "Boltund",
  "speciesId": "boltund",
  "baseStats": {
    "atk": 197,
    "def": 131,
    "hp": 170
  },
  "defaultIvs": {
    "1500": {
      "level": 25,
      "ivs": {
        "atk": 7,
        "def": 15,
        "hp": 15
      }
    },
    "2500": {
      "level": 50,
      "ivs": {
        "atk": 15,
        "def": 15,
        "hp": 15
      }
    }
  },
  "types": [
    "electric"
  ],
  "fastMoves": [
    "SPARK",
    "BITE"
  ],
  "chargedMoves": [
    "CRUNCH",
    "THUNDER"
  ],
  "released": false
}